Metadata-Version: 2.1
Name: pytest-priority
Version: 0.1.0
Summary: pytest plugin for add priority for tests
Home-page: http://github.com/hanzhichao/pytest-priority
Author: Han Zhichao
Author-email: superhin@126.com
License: MIT License
